ChromeDevTools
tests
