Metadata-Version: 2.1
Name: ChromeDevTools
Version: 0.3.6
Summary: Async Chrome DevTools
Home-page: https://github.com/codedumps/async-chrome-dev-tools
Author: Sergey M
Author-email: tz4678@gmail.com
License: NO F*CKING LICENSE
